boxygenapi/__init__.py
boxygenapi/boxygen/__init__.py
boxygenapi/boxygen/builder/__init__.py
boxygenapi/boxygen/builder/v1/__init__.py
boxygen_api-0.0.1rc7.dist-info/LICENSE.txt
boxygen_api-0.0.1rc7.dist-info/METADATA
boxygen_api-0.0.1rc7.dist-info/WHEEL
boxygen_api-0.0.1rc7.dist-info/top_level.txt
boxygen_api-0.0.1rc7.dist-info/RECORD
