Metadata-Version: 2.1
Name: boxygen-api
Version: 0.0.1rc7
Summary: The Boxygen base API client for Python 3
Home-page: https://github.com/nitrictech/boxygen-apis
Author: Nitric
Author-email: maintainers@nitric.io
License: UNKNOWN
Platform: UNKNOWN
Classifier: Programming Language :: Python :: 3
Classifier: Operating System :: OS Independent
Requires-Python: >=3.7
Requires-Dist: protobuf (==3.13.0)
Requires-Dist: betterproto (==2.0.0b3)
Requires-Dist: asyncio
Provides-Extra: dev
Requires-Dist: betterproto[compiler] (==2.0.0b3) ; extra == 'dev'
Requires-Dist: grpcio-tools (==1.33.2) ; extra == 'dev'
Requires-Dist: twine (==3.2.0) ; extra == 'dev'
